fnmatch.py
setup.py
micropython_fnmatch.egg-info/PKG-INFO
micropython_fnmatch.egg-info/SOURCES.txt
micropython_fnmatch.egg-info/dependency_links.txt
micropython_fnmatch.egg-info/requires.txt
micropython_fnmatch.egg-info/top_level.txt